LICENCE
boa_contrast/__init__.py
boa_contrast/__main__.py
boa_contrast/cli.py
boa_contrast/commands.py
boa_contrast/features/__init__.py
boa_contrast/features/feature_builder.py
boa_contrast/ml/__init__.py
boa_contrast/ml/contrast_recognition.py
boa_contrast/models/KM_in_GI_HistGradientBoostingClassifier_2class_2023-07-18/features_KM_in_GI_HistGradientBoostingClassifier_2class_2023-07-18.pkl
boa_contrast/models/KM_in_GI_HistGradientBoostingClassifier_2class_2023-07-18/model_KM_in_GI_HistGradientBoostingClassifier_2class_2023-07-18_0.pkl
boa_contrast/models/KM_in_GI_HistGradientBoostingClassifier_2class_2023-07-18/model_KM_in_GI_HistGradientBoostingClassifier_2class_2023-07-18_1.pkl
boa_contrast/models/KM_in_GI_HistGradientBoostingClassifier_2class_2023-07-18/model_KM_in_GI_HistGradientBoostingClassifier_2class_2023-07-18_2.pkl
boa_contrast/models/KM_in_GI_HistGradientBoostingClassifier_2class_2023-07-18/model_KM_in_GI_HistGradientBoostingClassifier_2class_2023-07-18_3.pkl
boa_contrast/models/KM_in_GI_HistGradientBoostingClassifier_2class_2023-07-18/model_KM_in_GI_HistGradientBoostingClassifier_2class_2023-07-18_4.pkl
boa_contrast/models/real_IV_class_HistGradientBoostingClassifier_5class_2023-07-20/features_real_IV_class_HistGradientBoostingClassifier_5class_2023-07-20.pkl
boa_contrast/models/real_IV_class_HistGradientBoostingClassifier_5class_2023-07-20/model_real_IV_class_HistGradientBoostingClassifier_5class_2023-07-20_0.pkl
boa_contrast/models/real_IV_class_HistGradientBoostingClassifier_5class_2023-07-20/model_real_IV_class_HistGradientBoostingClassifier_5class_2023-07-20_1.pkl
boa_contrast/models/real_IV_class_HistGradientBoostingClassifier_5class_2023-07-20/model_real_IV_class_HistGradientBoostingClassifier_5class_2023-07-20_2.pkl
boa_contrast/models/real_IV_class_HistGradientBoostingClassifier_5class_2023-07-20/model_real_IV_class_HistGradientBoostingClassifier_5class_2023-07-20_3.pkl
boa_contrast-0.1.4.dist-info/METADATA
boa_contrast-0.1.4.dist-info/WHEEL
boa_contrast-0.1.4.dist-info/entry_points.txt
boa_contrast-0.1.4.dist-info/RECORD
