Metadata-Version: 2.1
Name: boa-contrast
Version: 0.1.4
Summary: 
Home-page: https://github.com/UMEssen/BOA-Contrast
License: MIT
Keywords: python,contrast,intravenous,gastrointestinal tract,CT,machine learning
Author: Giulia Baldini
Author-email: Giulia.Baldini@uk-essen.de
Requires-Python: >=3.8,<3.11
Classifier: License :: OSI Approved :: MIT License
Classifier: Programming Language :: Python :: 3
Classifier: Programming Language :: Python :: 3.8
Classifier: Programming Language :: Python :: 3.9
Classifier: Programming Language :: Python :: 3.10
Provides-Extra: totalsegmentator
Requires-Dist: connected-components-3d (>=3.10.2,<4.0.0)
Requires-Dist: opencv-python (>=4.5.5.64,<5.0.0.0)
Requires-Dist: pandas (>=1.5.2,<2.0.0)
Requires-Dist: scikit-image (>=0.19.3,<0.20.0)
Requires-Dist: scikit-learn (>=1.1.2,<2.0.0)
Requires-Dist: simpleitk (>=2.2.0,<3.0.0)
Requires-Dist: threadpoolctl (>=3.1.0,<4.0.0)
Requires-Dist: totalsegmentator (==1.5.5) ; extra == "totalsegmentator"
Project-URL: Repository, https://github.com/UMEssen/BOA-Contrast
